ipylab/__init__.py
ipylab/_frontend.py
ipylab/_version.py
ipylab/commands.py
ipylab/icon.py
ipylab/jupyterfrontend.py
ipylab/menu.py
ipylab/sessions.py
ipylab/shell.py
ipylab/toolbar.py
ipylab/widgets.py
ipylab-1.1.0.data/data/share/jupyter/labextensions/ipylab/package.json
ipylab-1.1.0.data/data/share/jupyter/labextensions/ipylab/static/122.101ecc78f02bd37c57df.js
ipylab-1.1.0.data/data/share/jupyter/labextensions/ipylab/static/380.a747a09ef60bfa7eb001.js
ipylab-1.1.0.data/data/share/jupyter/labextensions/ipylab/static/442.3677eb0b1f1b552ec5c4.js
ipylab-1.1.0.data/data/share/jupyter/labextensions/ipylab/static/509.390d38b00e8c249bf07f.js
ipylab-1.1.0.data/data/share/jupyter/labextensions/ipylab/static/552.97a642707574b0ca4173.js
ipylab-1.1.0.data/data/share/jupyter/labextensions/ipylab/static/692.429d4bf8669793dac721.js
ipylab-1.1.0.data/data/share/jupyter/labextensions/ipylab/static/692.429d4bf8669793dac721.js.LICENSE.txt
ipylab-1.1.0.data/data/share/jupyter/labextensions/ipylab/static/remoteEntry.a623ad007fc3f6deb8ab.js
ipylab-1.1.0.data/data/share/jupyter/labextensions/ipylab/static/style.js
ipylab-1.1.0.data/data/share/jupyter/labextensions/ipylab/static/third-party-licenses.json
ipylab-1.1.0.data/data/share/jupyter/labextensions/ipylab/install.json
ipylab-1.1.0.dist-info/METADATA
ipylab-1.1.0.dist-info/WHEEL
ipylab-1.1.0.dist-info/licenses/LICENSE
ipylab-1.1.0.dist-info/RECORD
