Metadata-Version: 2.4
Name: ipylab
Version: 1.1.0
Dynamic: Keywords
Summary: Control JupyterLab from Python notebooks
Project-URL: Homepage, https://github.com/jtpio/ipylab
Project-URL: Bug Tracker, https://github.com/jtpio/ipylab/issues
Project-URL: Repository, https://github.com/jtpio/ipylab
Author: ipylab contributors
License: Copyright (c) 2020 ipylab contributors
License-File: LICENSE
Classifier: Framework :: Jupyter
Classifier: Framework :: Jupyter :: JupyterLab
Classifier: Framework :: Jupyter :: JupyterLab :: 4
Classifier: Framework :: Jupyter :: JupyterLab :: Extensions
Classifier: Framework :: Jupyter :: JupyterLab :: Extensions :: Prebuilt
Classifier: License :: OSI Approved :: BSD License
Classifier: Programming Language :: Python
Classifier: Programming Language :: Python :: 3
Classifier: Programming Language :: Python :: 3.8
Classifier: Programming Language :: Python :: 3.9
Classifier: Programming Language :: Python :: 3.10
Classifier: Programming Language :: Python :: 3.11
Classifier: Programming Language :: Python :: 3.12
Requires-Python: >=3.8
Requires-Dist: ipywidgets<9,>=7.6.0
